harisad_auth/__init__.py
harisad_auth/hasher.py
harisad_auth/manager.py
harisad_auth/models.py
harisad_auth-0.1.0.dist-info/licenses/LICENSE
harisad_auth-0.1.0.dist-info/METADATA
harisad_auth-0.1.0.dist-info/WHEEL
harisad_auth-0.1.0.dist-info/top_level.txt
harisad_auth-0.1.0.dist-info/RECORD
