Metadata-Version: 2.4
Name: harisad_auth
Version: 0.1.0
Summary: Library Auth dengan Double Hashing Argon2id + HMAC-SHA512
Author: Haris Mujianto
Classifier: Programming Language :: Python :: 3
Classifier: License :: OSI Approved :: MIT License
Classifier: Operating System :: OS Independent
Requires-Python: >=3.7
License-File: LICENSE
Requires-Dist: argon2-cffi>=21.1.0
Dynamic: author
Dynamic: classifier
Dynamic: description
Dynamic: description-content-type
Dynamic: license-file
Dynamic: requires-dist
Dynamic: requires-python
Dynamic: summary
